twiddle_rom.sv

module twiddle_rom #(
    parameter N = 1024,
    parameter DEPTH = N/2,
    parameter ABITS = 9, //address bits
    parameter WIDTH = 16 //width of the twiddle factor in bits
)(
    input logic clk,
    input logic [ABITS-1:0] addr,
    output logic signed [WIDTH-1:0] wr,
    output logic signed [WIDTH-1:0] wi
);
    logic signed [WIDTH-1:0] rom_real[0:DEPTH-1];
    logic signed [WIDTH-1:0] rom_imag[0:DEPTH-1];

    initial begin
        $readmemh("twiddle_real.hex", rom_real);
        $readmemh("twiddle_imag.hex", rom_imag);
    end

    always_ff @(posedge clk)begin
        wr<=rom_real[addr];
        wi<=rom_imag[addr];
    end

endmodule

twiddle_romtb.sv
`timescale 1ns/1ps

module tb_twiddle_rom;

    parameter ABITS = 9;
    parameter WIDTH = 16;

    logic clk;
    logic [ABITS-1:0] addr;
    logic signed [WIDTH-1:0] wr;
    logic signed [WIDTH-1:0] wi;

    // instantiate ROM
    twiddle_rom #(
        .N(1024),
        .DEPTH(512),
        .ABITS(ABITS),
        .WIDTH(WIDTH)
    ) dut (
        .clk(clk),
        .addr(addr),
        .wr(wr),
        .wi(wi)
    );

    // clock
    always #5 clk = ~clk;

    initial begin
        $dumpfile("tb_twiddle_rom.vcd");
        $dumpvars(0, tb_twiddle_rom);

        clk  = 0;
        addr = 0;

        @(posedge clk);
        addr = 9'd0;
        @(posedge clk); // wait 1 cycle for registered read
        $display("Test 1 - W^0:");
        $display("  wr = %0d (expect 32767)", wr);
        $display("  wi = %0d (expect 0)",     wi);

        @(posedge clk);
        addr = 9'd256;
        @(posedge clk);
        $display("Test 2 - W^256 (should be 0 - j1.0):");
        $display("  wr = %0d (expect 0)",      wr);
        $display("  wi = %0d (expect -32768)", wi);

        @(posedge clk);
        addr = 9'd128;
        @(posedge clk);
        $display("Test 3 - W^128 (should be 0.707 - j0.707):");
        $display("  wr = %0d (expect ~23170)",  wr);
        $display("  wi = %0d (expect ~-23170)", wi);

        $display("Test 4 - address sweep:");
        for (int i = 0; i < 4; i++) begin
            @(posedge clk);
            addr = i;
            @(posedge clk);
            $display("  addr=%0d: wr=%0d wi=%0d", addr, wr, wi);
        end

        $finish;
    end

endmodule

tb_twiddle_rom.vcd
$date
	Tue Jun 16 17:29:30 2026
$end
$version
	Icarus Verilog
$end
$timescale
	1ps
$end
$scope module tb_twiddle_rom $end
$var wire 16 ! wr [15:0] $end
$var wire 16 " wi [15:0] $end
$var parameter 32 # ABITS $end
$var parameter 32 $ WIDTH $end
$var reg 9 % addr [8:0] $end
$var reg 1 & clk $end
$scope module dut $end
$var wire 9 ' addr [8:0] $end
$var wire 1 & clk $end
$var parameter 32 ( ABITS $end
$var parameter 32 ) DEPTH $end
$var parameter 32 * N $end
$var parameter 32 + WIDTH $end
$var reg 16 , wi [15:0] $end
$var reg 16 - wr [15:0] $end
$upscope $end
$scope begin $ivl_for_loop0 $end
$var integer 32 . i [31:0] $end
$upscope $end
$upscope $end
$enddefinitions $end
$comment Show the parameter values. $end
$dumpall
b10000 +
b10000000000 *
b1000000000 )
b1001 (
b10000 $
b1001 #
$end
#0
$dumpvars
b0 .
bx -
bx ,
b0 '
0&
b0 %
bx "
bx !
$end
#5000
b0 "
b0 ,
b111111111111111 !
b111111111111111 -
1&
#10000
0&
#15000
1&
#20000
0&
#25000
b1000000000000001 "
b1000000000000001 ,
b0 !
b0 -
b100000000 %
b100000000 '
1&
#30000
0&
#35000
1&
#40000
0&
#45000
b1010010101111110 "
b1010010101111110 ,
b101101010000010 !
b101101010000010 -
b10000000 %
b10000000 '
1&
#50000
0&
#55000
1&
#60000
0&
#65000
b0 "
b0 ,
b111111111111111 !
b111111111111111 -
b0 %
b0 '
1&
#70000
0&
#75000
b1 .
1&
#80000
0&
#85000
b1111111100110111 "
b1111111100110111 ,
b111111111111110 !
b111111111111110 -
b1 %
b1 '
1&
#90000
0&
#95000
b10 .
1&
#100000
0&
#105000
b1111111001101110 "
b1111111001101110 ,
b111111111111101 !
b111111111111101 -
b10 %
b10 '
1&
#110000
0&
#115000
b11 .
1&
#120000
0&
#125000
b1111110110100101 "
b1111110110100101 ,
b111111111111001 !
b111111111111001 -
b11 %
b11 '
1&
#130000
0&
#135000
b100 .
1&
